ancile/LICENSE.py
ancile/__init__.py
ancile/cli.py
ancile/contributing.py
ancile/git_service.py
ancile/output_service.py
ancile/risk_analyzer.py
ancile-1.0.1.dist-info/LICENSE
ancile-1.0.1.dist-info/METADATA
ancile-1.0.1.dist-info/WHEEL
ancile-1.0.1.dist-info/entry_points.txt
ancile-1.0.1.dist-info/top_level.txt
ancile-1.0.1.dist-info/RECORD
