Metadata-Version: 2.2
Name: ancile
Version: 1.0.1
Summary: Ancile is a release risk assessment tool that analyzes differences between Git tags and evaluates changes based on configurable risk categories.
Author-email: Leading Works SàRL <admin@leading.works>
License: GPL-3.0-only
Project-URL: Homepage, https://gitlab.com/leading-works/floss/ancile
Classifier: Programming Language :: Python :: 3
Classifier: License :: OSI Approved :: GNU General Public License v3 (GPLv3)
Classifier: Operating System :: OS Independent
Requires-Python: >=3.12
License-File: LICENSE
Requires-Dist: click>=8.1.8
Requires-Dist: GitPython>=3.1.44
Requires-Dist: PyYAML>=6.0.2
Requires-Dist: rich>=13.9.4
Requires-Dist: toml>=0.10.2
Provides-Extra: dev
Requires-Dist: pytest>=8.3.5; extra == "dev"
Requires-Dist: pytest-bdd>=8.1.0; extra == "dev"
Requires-Dist: pytest-console-scripts>=1.4.1; extra == "dev"
Requires-Dist: pytest-cov>=6.0.0; extra == "dev"
Requires-Dist: pytest-html>=4.1.1; extra == "dev"
Requires-Dist: pytest-xdist>=3.6.1; extra == "dev"
Requires-Dist: black>=25.1.0; extra == "dev"
Requires-Dist: flake8>=7.1.2; extra == "dev"
Requires-Dist: mypy>=1.15.0; extra == "dev"
